crexperium/__init__.py
crexperium/client.py
crexperium/config.py
crexperium/exceptions.py
crexperium/models/__init__.py
crexperium/models/activity.py
crexperium/models/contact.py
crexperium/models/deal.py
crexperium/models/event.py
crexperium/resources/__init__.py
crexperium/resources/activities.py
crexperium/resources/base.py
crexperium/resources/contacts.py
crexperium/resources/deals.py
crexperium/resources/events.py
crexperium/utils/__init__.py
crexperium/utils/http.py
crexperium-1.1.0.dist-info/licenses/LICENSE
crexperium-1.1.0.dist-info/METADATA
crexperium-1.1.0.dist-info/WHEEL
crexperium-1.1.0.dist-info/top_level.txt
crexperium-1.1.0.dist-info/RECORD
