Metadata-Version: 2.4
Name: crexperium
Version: 1.1.0
Summary: Official Python SDK for Crexperium CRM API
Home-page: https://github.com/crexperium/crexperium-python-sdk
Author: Crexperium Team
Author-email: Crexperium Team <support@crexperium.com>
License: MIT
Project-URL: Homepage, https://github.com/crexperium/crexperium-python-sdk
Project-URL: Documentation, https://docs.crexperium.com
Project-URL: Repository, https://github.com/crexperium/crexperium-python-sdk
Project-URL: Bug Reports, https://github.com/crexperium/crexperium-python-sdk/issues
Keywords: crm,api,sdk,crexperium
Classifier: Development Status :: 5 - Production/Stable
Classifier: Intended Audience :: Developers
Classifier: License :: OSI Approved :: MIT License
Classifier: Operating System :: OS Independent
Classifier: Programming Language :: Python :: 3
Classifier: Programming Language :: Python :: 3.8
Classifier: Programming Language :: Python :: 3.9
Classifier: Programming Language :: Python :: 3.10
Classifier: Programming Language :: Python :: 3.11
Classifier: Programming Language :: Python :: 3.12
Requires-Python: >=3.8
License-File: LICENSE
Requires-Dist: requests>=2.28.0
Provides-Extra: dev
Requires-Dist: pytest>=7.0.0; extra == "dev"
Requires-Dist: pytest-cov>=4.0.0; extra == "dev"
Requires-Dist: black>=22.0.0; extra == "dev"
Requires-Dist: flake8>=5.0.0; extra == "dev"
Requires-Dist: mypy>=1.0.0; extra == "dev"
Dynamic: author
Dynamic: home-page
Dynamic: license-file
Dynamic: requires-python
